{"nodes": [{"group": "all", "index": 0, "name": "application"}, {"group": "all", "index": 1, "name": "approach"}, {"group": "all", "index": 2, "name": "aspect"}, {"group": "all", "index": 3, "name": "attribute"}, {"group": "all", "index": 4, "name": "base"}, {"group": "all", "index": 5, "name": "case"}, {"group": "all", "index": 6, "name": "cation"}, {"group": "all", "index": 7, "name": "change"}, {"group": "all", "index": 8, "name": "component"}, {"group": "all", "index": 9, "name": "composition"}, {"group": "all", "index": 10, "name": "connector"}, {"group": "all", "index": 11, "name": "design"}, {"group": "all", "index": 12, "name": "development"}, {"group": "all", "index": 13, "name": "discipline"}, {"group": "all", "index": 14, "name": "engineering"}, {"group": "all", "index": 15, "name": "fault"}, {"group": "all", "index": 16, "name": "interaction"}, {"group": "all", "index": 17, "name": "interface"}, {"group": "all", "index": 18, "name": "knowledge"}, {"group": "all", "index": 19, "name": "level"}, {"group": "all", "index": 20, "name": "log"}, {"group": "all", "index": 21, "name": "medium"}, {"group": "all", "index": 22, "name": "message"}, {"group": "all", "index": 23, "name": "model"}, {"group": "all", "index": 24, "name": "object"}, {"group": "all", "index": 25, "name": "process"}, {"group": "all", "index": 26, "name": "project"}, {"group": "all", "index": 27, "name": "quality"}, {"group": "all", "index": 28, "name": "record"}, {"group": "all", "index": 29, "name": "requirement"}, {"group": "all", "index": 30, "name": "risk"}, {"group": "all", "index": 31, "name": "service"}, {"group": "all", "index": 32, "name": "software"}, {"group": "all", "index": 33, "name": "speci"}, {"group": "all", "index": 34, "name": "state"}, {"group": "all", "index": 35, "name": "study"}, {"group": "all", "index": 36, "name": "system"}, {"group": "all", "index": 37, "name": "technique"}, {"group": "all", "index": 38, "name": "time"}, {"group": "all", "index": 39, "name": "transition"}, {"group": "all", "index": 40, "name": "user"}, {"group": "all", "index": 41, "name": "web"}], "links": [{"source": 32, "target": 14, "value": 962}, {"source": 32, "target": 12, "value": 770}, {"source": 8, "target": 31, "value": 670}, {"source": 8, "target": 0, "value": 616}, {"source": 8, "target": 36, "value": 562}, {"source": 14, "target": 41, "value": 554}, {"source": 8, "target": 17, "value": 512}, {"source": 32, "target": 36, "value": 512}, {"source": 36, "target": 23, "value": 452}, {"source": 39, "target": 34, "value": 438}, {"source": 19, "target": 4, "value": 414}, {"source": 8, "target": 23, "value": 408}, {"source": 14, "target": 13, "value": 384}, {"source": 8, "target": 2, "value": 380}, {"source": 38, "target": 36, "value": 318}, {"source": 32, "target": 29, "value": 318}, {"source": 20, "target": 28, "value": 316}, {"source": 32, "target": 25, "value": 308}, {"source": 36, "target": 25, "value": 304}, {"source": 3, "target": 27, "value": 304}, {"source": 32, "target": 11, "value": 300}, {"source": 12, "target": 36, "value": 298}, {"source": 23, "target": 25, "value": 298}, {"source": 31, "target": 30, "value": 296}, {"source": 2, "target": 0, "value": 294}, {"source": 35, "target": 5, "value": 290}, {"source": 32, "target": 41, "value": 284}, {"source": 12, "target": 25, "value": 282}, {"source": 9, "target": 8, "value": 280}, {"source": 31, "target": 41, "value": 274}, {"source": 12, "target": 23, "value": 270}, {"source": 15, "target": 31, "value": 266}, {"source": 32, "target": 35, "value": 264}, {"source": 32, "target": 8, "value": 256}, {"source": 12, "target": 26, "value": 254}, {"source": 8, "target": 10, "value": 254}, {"source": 41, "target": 13, "value": 246}, {"source": 17, "target": 40, "value": 244}, {"source": 32, "target": 23, "value": 242}, {"source": 36, "target": 34, "value": 238}, {"source": 32, "target": 26, "value": 238}, {"source": 8, "target": 16, "value": 238}, {"source": 8, "target": 22, "value": 236}, {"source": 1, "target": 36, "value": 234}, {"source": 7, "target": 36, "value": 234}, {"source": 33, "target": 6, "value": 232}, {"source": 36, "target": 29, "value": 230}, {"source": 32, "target": 18, "value": 230}, {"source": 24, "target": 21, "value": 230}, {"source": 37, "target": 29, "value": 228}]}