{"nodes": [{"group": "all", "index": 0, "name": "adjacency"}, {"group": "all", "index": 1, "name": "algorithm"}, {"group": "all", "index": 2, "name": "attack"}, {"group": "all", "index": 3, "name": "b"}, {"group": "all", "index": 4, "name": "bipartite"}, {"group": "all", "index": 5, "name": "block"}, {"group": "all", "index": 6, "name": "case"}, {"group": "all", "index": 7, "name": "complexity"}, {"group": "all", "index": 8, "name": "e"}, {"group": "all", "index": 9, "name": "edge"}, {"group": "all", "index": 10, "name": "g"}, {"group": "all", "index": 11, "name": "graph"}, {"group": "all", "index": 12, "name": "group"}, {"group": "all", "index": 13, "name": "l"}, {"group": "all", "index": 14, "name": "line"}, {"group": "all", "index": 15, "name": "m"}, {"group": "all", "index": 16, "name": "matrix"}, {"group": "all", "index": 17, "name": "member"}, {"group": "all", "index": 18, "name": "message"}, {"group": "all", "index": 19, "name": "network"}, {"group": "all", "index": 20, "name": "neuron"}, {"group": "all", "index": 21, "name": "node"}, {"group": "all", "index": 22, "name": "number"}, {"group": "all", "index": 23, "name": "p"}, {"group": "all", "index": 24, "name": "path"}, {"group": "all", "index": 25, "name": "point"}, {"group": "all", "index": 26, "name": "problem"}, {"group": "all", "index": 27, "name": "r"}, {"group": "all", "index": 28, "name": "resource"}, {"group": "all", "index": 29, "name": "set"}, {"group": "all", "index": 30, "name": "spike"}, {"group": "all", "index": 31, "name": "system"}, {"group": "all", "index": 32, "name": "time"}, {"group": "all", "index": 33, "name": "topology"}, {"group": "all", "index": 34, "name": "tree"}, {"group": "all", "index": 35, "name": "v"}, {"group": "all", "index": 36, "name": "vertex"}], "links": [{"source": 24, "target": 21, "value": 582}, {"source": 27, "target": 13, "value": 414}, {"source": 11, "target": 21, "value": 370}, {"source": 10, "target": 11, "value": 342}, {"source": 24, "target": 1, "value": 332}, {"source": 18, "target": 21, "value": 324}, {"source": 27, "target": 21, "value": 306}, {"source": 9, "target": 11, "value": 276}, {"source": 24, "target": 11, "value": 272}, {"source": 1, "target": 11, "value": 262}, {"source": 27, "target": 24, "value": 258}, {"source": 30, "target": 20, "value": 254}, {"source": 22, "target": 21, "value": 250}, {"source": 4, "target": 11, "value": 244}, {"source": 32, "target": 21, "value": 244}, {"source": 19, "target": 21, "value": 240}, {"source": 7, "target": 1, "value": 240}, {"source": 8, "target": 9, "value": 234}, {"source": 24, "target": 23, "value": 230}, {"source": 23, "target": 3, "value": 226}, {"source": 32, "target": 1, "value": 222}, {"source": 14, "target": 25, "value": 218}, {"source": 24, "target": 26, "value": 216}, {"source": 1, "target": 21, "value": 214}, {"source": 36, "target": 11, "value": 214}, {"source": 12, "target": 17, "value": 212}, {"source": 9, "target": 21, "value": 208}, {"source": 26, "target": 1, "value": 202}, {"source": 0, "target": 16, "value": 202}, {"source": 9, "target": 36, "value": 200}, {"source": 6, "target": 23, "value": 198}, {"source": 8, "target": 23, "value": 196}, {"source": 31, "target": 23, "value": 194}, {"source": 19, "target": 33, "value": 186}, {"source": 9, "target": 22, "value": 180}, {"source": 16, "target": 11, "value": 178}, {"source": 5, "target": 21, "value": 178}, {"source": 21, "target": 28, "value": 176}, {"source": 9, "target": 29, "value": 172}, {"source": 15, "target": 21, "value": 170}, {"source": 6, "target": 24, "value": 170}, {"source": 35, "target": 36, "value": 166}, {"source": 10, "target": 36, "value": 166}, {"source": 24, "target": 36, "value": 166}, {"source": 21, "target": 13, "value": 166}, {"source": 14, "target": 1, "value": 166}, {"source": 27, "target": 23, "value": 164}, {"source": 9, "target": 10, "value": 158}, {"source": 34, "target": 1, "value": 158}, {"source": 19, "target": 2, "value": 158}]}